kak_rope/__init__.py
kak_rope-0.3.0.dist-info/entry_points.txt
kak_rope-0.3.0.dist-info/LICENSE
kak_rope-0.3.0.dist-info/WHEEL
kak_rope-0.3.0.dist-info/METADATA
kak_rope-0.3.0.dist-info/RECORD
