Metadata-Version: 2.1
Name: kak-rope
Version: 0.3.0
Summary: Python refactoring actions for kakoune
Home-page: https://git.sr.ht/~dmerej/kak-rope
License: BSD-3-Clause
Author: Dimitri Merejkowsky
Author-email: dimitri@dmerej.info
Requires-Python: >=3.6.2,<4.0.0
Classifier: License :: OSI Approved :: BSD License
Classifier: Programming Language :: Python :: 3
Classifier: Programming Language :: Python :: 3.10
Classifier: Programming Language :: Python :: 3.7
Classifier: Programming Language :: Python :: 3.8
Classifier: Programming Language :: Python :: 3.9
Requires-Dist: rope (>=0.19.0,<0.20.0)
Project-URL: Changelog, https://git.sr.ht/~dmerej/kak-rope/tree/main/item/CHANGELOG.md
Project-URL: Issues, https://todo.sr.ht/~dmerej/kak-rope
Project-URL: Repository, https://git.sr.ht/~dmerej/kak-rope
